ghlightning/__init__.py
ghlightning/_ghlightning.py
ghlightning/errors.py
ghlightning-1.0.9.dist-info/LICENSE
ghlightning-1.0.9.dist-info/METADATA
ghlightning-1.0.9.dist-info/WHEEL
ghlightning-1.0.9.dist-info/top_level.txt
ghlightning-1.0.9.dist-info/RECORD
