Metadata-Version: 2.1
Name: ghlightning
Version: 1.0.9
Summary: Github scraper.
Home-page: https://github.com/7azabet/lightning
Author: Nader Ahmed
Author-email: nad3rahm3d@gmail.com
License: MIT License        
Project-URL: Bug Tracker, https://github.com/7azabet/lightning/issues
Keywords: ghlightning github_scrapper scrapper github info NaderAhmed nad3rahm3d
Platform: Windows
Platform: Linux
Platform: Solaris
Platform: Mac OS-X
Platform: Unix
Classifier: Programming Language :: Python :: 3
Classifier: License :: OSI Approved :: MIT License
Classifier: Operating System :: OS Independent
Requires-Python: >=3.6
License-File: LICENSE
Requires-Dist: urllib3
Requires-Dist: requests
Requires-Dist: bs4
Requires-Dist: pathlib
Requires-Dist: countryinfo
Requires-Dist: user-agent
